{
  "ComponentIndexes": {},
  "ControlUniqueGuids": {},
  "ControlUniqueIds": {
    "ActionFlowGallery": 582,
    "AlertInfoContainer": 408,
    "AlertInfoContainer_1": 426,
    "AlertInfoContainerSmall": 399,
    "AlertInfoContainerSmall_1": 417,
    "AlertSuccessContainer": 403,
    "AlertSuccessContainer_1": 421,
    "AlertSuccessContainerSmall": 395,
    "AlertSuccessContainerSmall_1": 413,
    "App": 1,
    "Attachment_Excel": 81,
    "Attachment_Excel2": 546,
    "Attachment_Zip": 90,
    "Attachment_Zip2": 562,
    "BackgroundRectangle_6": 49,
    "BottomContainer": 153,
    "BottomContainer_2": 601,
    "BtnDashed": 270,
    "BtnDashed_1": 293,
    "BtnDashed_2": 318,
    "BtnDashed_3": 279,
    "BtnDashed_4": 256,
    "BtnDashed_5": 271,
    "BtnDashed_6": 302,
    "BtnDashed_7": 294,
    "BtnDashed_8": 319,
    "BtnDashedIcon": 327,
    "BtnDashedIcon_1": 337,
    "BtnDashedIcon_2": 328,
    "BtnDashedIcon_3": 333,
    "BtnDashedIcon_4": 338,
    "BtnDashedIcon_5": 341,
    "BtnDashedIconOnly": 272,
    "BtnDashedIconOnly_1": 295,
    "BtnDashedIconOnly_2": 281,
    "BtnDashedIconOnly_3": 258,
    "BtnDashedIconOnly_4": 304,
    "BtnDashedIconOnly_5": 320,
    "BtnDashedLg_1": 239,
    "BtnDashedLg_2": 240,
    "BtnDashedLgIconOnly": 241,
    "BtnDefault": 267,
    "BtnDefault_1": 290,
    "BtnDefault_17": 144,
    "BtnDefault_18": 108,
    "BtnDefault_19": 596,
    "BtnDefault_2": 268,
    "BtnDefault_20": 503,
    "BtnDefault_21": 504,
    "BtnDefault_22": 505,
    "BtnDefault_23": 54,
    "BtnDefault_24": 55,
    "BtnDefault_25": 56,
    "BtnDefault_26": 118,
    "BtnDefault_27": 128,
    "BtnDefault_3": 291,
    "BtnDefault_4": 315,
    "BtnDefault_5": 316,
    "BtnDefaultIcon": 325,
    "BtnDefaultIcon_1": 335,
    "BtnDefaultIcon_2": 340,
    "BtnDefaultIconOnly": 269,
    "BtnDefaultIconOnly_1": 292,
    "BtnDefaultIconOnly_2": 317,
    "BtnDefaultIconOnly_3": 545,
    "BtnDefaultLg": 244,
    "BtnDefaultLg_12": 48,
    "BtnDefaultLg_13": 497,
    "BtnDefaultLg_6": 156,
    "BtnDefaultLg_7": 605,
    "BtnDefaultLg_8": 606,
    "BtnDefaultLg_9": 12,
    "BtnLgIcon": 324,
    "BtnLgIcon_1": 334,
    "BtnLgIcon_2": 339,
    "BtnLgIconOnly": 266,
    "BtnLgIconOnly_1": 289,
    "BtnLgIconOnly_2": 314,
    "BtnLink": 262,
    "BtnLink_1": 286,
    "BtnLink_2": 310,
    "BtnLink_3": 391,
    "BtnLink_4": 392,
    "BtnLinkLg": 249,
    "BtnPrimary": 264,
    "BtnPrimary_1": 265,
    "BtnPrimary_2": 312,
    "BtnPrimary_3": 288,
    "BtnPrimary_4": 313,
    "BtnPrimaryLg": 238,
    "BtnPrimaryLg_1": 242,
    "BtnPrimaryLg_10": 608,
    "BtnPrimaryLg_12": 47,
    "BtnPrimaryLg_13": 496,
    "BtnPrimaryLg_7": 157,
    "BtnPrimaryLg_8": 607,
    "BtnPrimaryLg_9": 11,
    "BtnPrimaryLgIcon": 329,
    "BtnPrimaryLgIconOnly": 243,
    "BtnPrimarySmall_2": 287,
    "BtnSecond": 276,
    "BtnSecond_1": 299,
    "BtnSecond_2": 277,
    "BtnSecond_3": 254,
    "BtnSecond_4": 300,
    "BtnSecondIcon": 326,
    "BtnSecondIcon_1": 332,
    "BtnSecondIcon_2": 336,
    "BtnSecondIconOnly": 278,
    "BtnSecondIconOnly_1": 255,
    "BtnSecondIconOnly_17": 146,
    "BtnSecondIconOnly_18": 598,
    "BtnSecondIconOnly_19": 110,
    "BtnSecondIconOnly_2": 301,
    "BtnSecondIconOnly_21": 33,
    "BtnSecondIconOnly_22": 120,
    "BtnSecondIconOnly_23": 475,
    "BtnSecondIconOnly_25": 130,
    "BtnSecondIconOnly_26": 458,
    "BtnText": 261,
    "BtnText_1": 285,
    "BtnTextLg": 248,
    "Button_large_10": 253,
    "Button_large_16": 280,
    "Button_large_17": 245,
    "Button_large_18": 257,
    "Button_large_19": 303,
    "canDesignGuide": 160,
    "Checkbox2": 362,
    "Checkbox2_1": 44,
    "Checkbox2_2": 27,
    "Checkbox2_3": 493,
    "Checkbox2_4": 486,
    "Circle1_4": 42,
    "Circle1_5": 25,
    "Circle1_6": 491,
    "Circle1_7": 484,
    "Circle2_10": 105,
    "Circle2_11": 585,
    "Circle2_12": 115,
    "Circle2_13": 125,
    "Circle2_14": 577,
    "Circle2_7": 141,
    "Circle2_8": 136,
    "Circle2_9": 593,
    "ComboBox1": 351,
    "ComboBox1_11": 148,
    "ComboBox1_12": 600,
    "ComboBox1_13": 112,
    "ComboBox1_14": 122,
    "ComboBox1_15": 132,
    "ComboBox1_5": 34,
    "ComboBox1_6": 476,
    "CommentLabel_1": 588,
    "CommentLabel_2": 589,
    "CommentsContainer": 99,
    "CommentsContainer_1": 571,
    "CompleteScreen": 3,
    "Container1": 82,
    "Container10_1": 498,
    "Container11_1": 155,
    "Container11_2": 603,
    "Container11_5": 46,
    "Container11_6": 495,
    "Container12": 533,
    "Container12_2": 537,
    "Container12_3": 77,
    "Container13": 538,
    "Container13_10": 64,
    "Container13_11": 67,
    "Container13_12": 508,
    "Container13_13": 511,
    "Container13_14": 514,
    "Container13_15": 517,
    "Container13_16": 520,
    "Container13_17": 523,
    "Container13_18": 526,
    "Container13_8": 58,
    "Container13_9": 61,
    "Container16_10": 455,
    "Container16_4": 20,
    "Container16_5": 21,
    "Container16_6": 469,
    "Container16_7": 470,
    "Container17_2": 29,
    "Container17_3": 471,
    "Container17_5": 456,
    "Container2": 382,
    "Container3": 92,
    "Container4": 8,
    "Container5": 87,
    "Container6": 547,
    "Container7": 563,
    "Container8": 73,
    "Container9": 535,
    "CopyIcon_3": 590,
    "CountDepartment": 31,
    "CountDepartment_1": 474,
    "CountLast": 30,
    "CountLast_1": 473,
    "crdButton": 226,
    "crdColor": 161,
    "crdComponent": 342,
    "crdFont": 433,
    "CreateGeneralFormScreen": 14,
    "DataCardValue2": 366,
    "DateBackground_2": 357,
    "DateLineLabel1_39": 361,
    "DatePicker1": 352,
    "Design elements": 162,
    "Design Guide Screen": 159,
    "DetailGeneralFormScreen": 449,
    "DownloadIcon_1": 558,
    "DownloadIcon_2": 541,
    "DownloadIcon_6": 462,
    "Dropdown1": 350,
    "Dropdown1_5": 142,
    "Dropdown1_6": 594,
    "Dropdown1_7": 106,
    "Dropdown1_8": 116,
    "Dropdown1_9": 126,
    "drpFilterDepartment_1": 76,
    "FileLabel_1": 560,
    "FileLabel_2": 540,
    "FileLabel_6": 463,
    "FillInContainer": 70,
    "FillInContainer_1": 529,
    "FilterLabelContainer": 96,
    "FilterLabelContainer_1": 568,
    "FlowActionStepContainer": 580,
    "FormNameContainer": 52,
    "FormNameContainer_1": 500,
    "FormNameLabel_1": 53,
    "FormNameLabel_2": 502,
    "FormNameLabel_5": 32,
    "FormNameLabel_6": 472,
    "FormNameLabel_8": 457,
    "Gallery_FormHistory_3": 459,
    "Gallery2_2": 39,
    "Gallery2_3": 22,
    "Gallery2_4": 488,
    "Gallery2_5": 481,
    "Gallery4": 386,
    "Gallery4_1": 440,
    "Gallery6_3": 553,
    "galleryTemplate1_2": 40,
    "galleryTemplate1_3": 23,
    "galleryTemplate1_4": 489,
    "galleryTemplate1_5": 482,
    "galleryTemplate2": 583,
    "galleryTemplate3": 368,
    "galleryTemplate3_1": 372,
    "galleryTemplate3_5": 36,
    "galleryTemplate3_6": 478,
    "galleryTemplate4": 387,
    "galleryTemplate4_1": 441,
    "galleryTemplate8_3": 554,
    "galleryTemplate8_7": 460,
    "GeneralFlowContainer": 139,
    "Group1": 432,
    "Group2_2": 330,
    "Group2_3": 331,
    "HeaderContainer_2": 450,
    "HeaderContainer_3": 4,
    "HeaderContainer_4": 15,
    "Hide_Pwd": 544,
    "Hide_Pwd_1": 557,
    "Hide_Pwd_5": 467,
    "HistoryContainer": 454,
    "Icon2_4": 451,
    "Icon2_5": 5,
    "Icon2_6": 16,
    "Icon3": 9,
    "Icon4_10": 282,
    "Icon4_11": 259,
    "Icon4_12": 305,
    "Icon4_13": 275,
    "Icon4_14": 298,
    "Icon4_15": 283,
    "Icon4_16": 251,
    "Icon4_17": 246,
    "Icon4_18": 252,
    "Icon4_19": 260,
    "Icon4_20": 250,
    "Icon4_21": 306,
    "Icon4_22": 321,
    "Icon4_23": 322,
    "Icon4_24": 323,
    "Icon4_30": 404,
    "Icon4_31": 409,
    "Icon4_32": 396,
    "Icon4_33": 400,
    "Icon4_34": 422,
    "Icon4_35": 414,
    "Icon4_36": 427,
    "Icon4_37": 418,
    "Icon4_6": 273,
    "Icon4_7": 296,
    "Icon4_8": 274,
    "Icon4_9": 297,
    "Icon5_2": 43,
    "Icon5_3": 26,
    "Icon5_4": 492,
    "Icon5_5": 485,
    "iconSuccess": 405,
    "iconSuccess_1": 410,
    "iconSuccess_2": 423,
    "iconSuccess_3": 428,
    "iconSuccess4": 398,
    "iconSuccess4_1": 402,
    "iconSuccess4_2": 416,
    "iconSuccess4_3": 420,
    "Image1": 452,
    "Image1_1": 17,
    "Image1_2": 6,
    "Image2": 532,
    "Image3": 567,
    "Image3_13": 464,
    "Image3_8": 561,
    "Image3_9": 539,
    "Image4_1": 91,
    "Image4_2": 78,
    "InfoContainer": 51,
    "InfoContainer_1": 499,
    "InfoContainer12_2": 57,
    "InfoContainer12_3": 507,
    "labColorCode": 187,
    "labColorCode_1": 196,
    "labColorCode_10": 213,
    "labColorCode_11": 216,
    "labColorCode_12": 219,
    "labColorCode_13": 222,
    "labColorCode_14": 225,
    "labColorCode_2": 205,
    "labColorCode_3": 188,
    "labColorCode_4": 197,
    "labColorCode_5": 206,
    "labColorCode_6": 212,
    "labColorCode_7": 189,
    "labColorCode_8": 198,
    "labColorCode_9": 207,
    "labColorName_1": 184,
    "labColorName_10": 204,
    "labColorName_11": 211,
    "labColorName_12": 215,
    "labColorName_13": 218,
    "labColorName_14": 221,
    "labColorName_15": 224,
    "labColorName_2": 193,
    "labColorName_3": 202,
    "labColorName_4": 185,
    "labColorName_5": 194,
    "labColorName_6": 203,
    "labColorName_7": 210,
    "labColorName_8": 186,
    "labColorName_9": 195,
    "Label1": 10,
    "Label1_1": 179,
    "Label1_10": 347,
    "Label1_11": 348,
    "Label1_12": 353,
    "Label1_129": 59,
    "Label1_13": 233,
    "Label1_130": 60,
    "Label1_131": 62,
    "Label1_132": 63,
    "Label1_133": 65,
    "Label1_134": 66,
    "Label1_135": 68,
    "Label1_136": 69,
    "Label1_137": 145,
    "Label1_138": 597,
    "Label1_139": 509,
    "Label1_14": 234,
    "Label1_140": 510,
    "Label1_141": 512,
    "Label1_142": 513,
    "Label1_143": 515,
    "Label1_144": 516,
    "Label1_145": 518,
    "Label1_146": 519,
    "Label1_147": 521,
    "Label1_148": 522,
    "Label1_149": 524,
    "Label1_15": 308,
    "Label1_150": 525,
    "Label1_151": 527,
    "Label1_152": 528,
    "Label1_153": 109,
    "Label1_154": 119,
    "Label1_155": 129,
    "Label1_16": 309,
    "Label1_17": 311,
    "Label1_18": 235,
    "Label1_19": 236,
    "Label1_2": 178,
    "Label1_20": 237,
    "Label1_21": 231,
    "Label1_22": 232,
    "Label1_23": 229,
    "Label1_24": 230,
    "Label1_25": 171,
    "Label1_26": 169,
    "Label1_27": 354,
    "Label1_28": 355,
    "Label1_29": 356,
    "Label1_3": 228,
    "Label1_30": 364,
    "Label1_31": 365,
    "Label1_32": 375,
    "Label1_33": 172,
    "Label1_34": 165,
    "Label1_35": 167,
    "Label1_36": 170,
    "Label1_37": 168,
    "Label1_38": 173,
    "Label1_39": 175,
    "Label1_4": 247,
    "Label1_40": 174,
    "Label1_41": 180,
    "Label1_42": 176,
    "Label1_43": 177,
    "Label1_44": 163,
    "Label1_45": 381,
    "Label1_46": 435,
    "Label1_47": 436,
    "Label1_48": 448,
    "Label1_49": 438,
    "Label1_5": 263,
    "Label1_50": 439,
    "Label1_51": 394,
    "Label1_52": 446,
    "Label1_53": 447,
    "Label1_54": 431,
    "Label1_6": 284,
    "Label1_7": 344,
    "Label1_73": 453,
    "Label1_74": 18,
    "Label1_75": 7,
    "Label1_8": 345,
    "Label1_9": 346,
    "Label10": 406,
    "Label10_1": 407,
    "Label10_10": 430,
    "Label10_11": 419,
    "Label10_2": 397,
    "Label10_3": 411,
    "Label10_4": 412,
    "Label10_5": 401,
    "Label10_6": 424,
    "Label10_7": 425,
    "Label10_8": 415,
    "Label10_9": 429,
    "Label12_7": 536,
    "Label2": 369,
    "Label2_1": 373,
    "Label2_5": 37,
    "Label2_6": 479,
    "Label3": 388,
    "Label3_1": 389,
    "Label3_2": 443,
    "Label3_3": 442,
    "Label4": 383,
    "Label4_1": 384,
    "Label4_2": 385,
    "Label5": 501,
    "Label6": 83,
    "Label6_1": 93,
    "Label6_17": 140,
    "Label6_18": 143,
    "Label6_19": 147,
    "Label6_2": 548,
    "Label6_20": 135,
    "Label6_21": 138,
    "Label6_22": 592,
    "Label6_23": 595,
    "Label6_24": 599,
    "Label6_25": 104,
    "Label6_26": 107,
    "Label6_27": 584,
    "Label6_28": 587,
    "Label6_29": 111,
    "Label6_3": 564,
    "Label6_30": 114,
    "Label6_31": 117,
    "Label6_32": 121,
    "Label6_33": 124,
    "Label6_34": 576,
    "Label6_35": 127,
    "Label6_36": 579,
    "Label6_39": 131,
    "Label6_4": 74,
    "Label6_5": 79,
    "Label6_6": 88,
    "Label7_10": 483,
    "Label7_11": 487,
    "Label7_4": 41,
    "Label7_5": 45,
    "Label7_6": 24,
    "Label7_7": 28,
    "Label7_8": 490,
    "Label7_9": 494,
    "Label9_22": 89,
    "Label9_23": 97,
    "Label9_24": 100,
    "Label9_25": 133,
    "Label9_26": 534,
    "Label9_27": 552,
    "Label9_28": 570,
    "Label9_29": 572,
    "Label9_30": 581,
    "Label9_31": 573,
    "Label9_33": 80,
    "Label9_34": 75,
    "lblTag": 376,
    "lblTag_1": 390,
    "lblTag_2": 377,
    "lblTag_3": 378,
    "lblTag_4": 379,
    "lblTag_5": 380,
    "LeftContainer12": 71,
    "LeftContainer12_1": 530,
    "LineRectangle_5": 154,
    "LineRectangle_6": 602,
    "MainflowContainer": 50,
    "NextStepContainer_1": 591,
    "PredefinedFlowContainer": 123,
    "Radio1": 363,
    "Rectangle1": 343,
    "Rectangle1_1": 307,
    "Rectangle1_2": 166,
    "Rectangle1_3": 164,
    "Rectangle1_4": 227,
    "Rectangle1_5": 434,
    "Rectangle2": 370,
    "Rectangle2_1": 374,
    "Rectangle2_5": 38,
    "Rectangle2_6": 480,
    "Rectangle3": 393,
    "Rectangle3_1": 444,
    "Rectangle4": 437,
    "Rectangle5_4": 137,
    "Rectangle5_6": 586,
    "Rectangle5_7": 578,
    "RightContainer": 102,
    "RightContainer_1": 574,
    "SampleFlowContainer": 103,
    "SelectUserContainer_2": 19,
    "SelectUserContainer_3": 468,
    "Show_Pwd": 543,
    "Show_Pwd_1": 556,
    "Show_Pwd_5": 466,
    "shpColor_1": 190,
    "shpColor_10": 209,
    "shpColor_11": 214,
    "shpColor_12": 217,
    "shpColor_13": 220,
    "shpColor_14": 223,
    "shpColor_15": 181,
    "shpColor_2": 182,
    "shpColor_3": 199,
    "shpColor_4": 191,
    "shpColor_5": 200,
    "shpColor_6": 208,
    "shpColor_7": 183,
    "shpColor_8": 192,
    "shpColor_9": 201,
    "StartFlowContainer": 134,
    "StartFlowContainer_1": 575,
    "Statuslbl": 506,
    "SubmitViewfillinBtn_6": 151,
    "SubmitViewGroup": 158,
    "SubmitViewInfo_6": 150,
    "SubmitViewRectangle_6": 149,
    "SubmitViewsubmitBtn_6": 152,
    "TabGallery3": 367,
    "TabGallery3_1": 371,
    "TabGallery3_5": 35,
    "TabGallery3_6": 477,
    "TemplateContainer": 113,
    "TemplateEndDate_1": 359,
    "TemplateStartDate_1": 358,
    "TextInput_FilterLabel": 98,
    "TextInput_FilterLabel_1": 569,
    "TextInput_FormMark": 101,
    "TextInput_FormPWD": 84,
    "TextInput_FormPWD_1": 85,
    "TextInput_zipPWD": 94,
    "TextInput_zipPWD_1": 95,
    "TextInput1": 13,
    "TextInput2": 349,
    "TextInput2_1": 445,
    "TextInput2_30": 549,
    "TextInput2_31": 565,
    "TextInput2_32": 542,
    "TextInput2_33": 559,
    "TextInput2_34": 604,
    "TextInput2_35": 550,
    "TextInput2_37": 566,
    "TextInput2_39": 465,
    "Toggle1": 360,
    "UploadAttachmentsContainer": 86,
    "UploadAttachmentsContainer_1": 551,
    "UploaderLabel_1": 555,
    "UploaderLabel_5": 461,
    "UploadTemplateContainer": 72,
    "UploadTemplateContainer_1": 531
  },
  "FunctionParamsInvariantScripts": {},
  "FunctionParamsInvariantScriptsOnInstances": {},
  "HeaderLastSavedDateTimeUTC": "09/26/2022 09:07:15",
  "IsLegacyComponentAllowGlobalScopeCase": false,
  "LocalConnectionIDReferences": {
    "a8533cc4-ffce-457e-bb55-36cb04d5b45e": "\"/providers/microsoft.powerapps/apis/shared_logicflows/connections/f3b366c9-ae33-4e98-8f4c-db28ef3d9a2c\"",
    "b0c44b9f-1553-4993-b73f-7463ecb07cb0": "\"/providers/microsoft.powerapps/apis/shared_logicflows/connections/5b299dd21406477db12fe23343be43f3-7c7547c680553065\"",
    "c63818b0-6a22-4c7d-8e8a-4c662dfaa20f": "\"/providers/microsoft.powerapps/apis/shared_office365users/connections/3c0a63a56a004f34a86910ac7d681d38\"",
    "ed5c50bd-bb07-4f5f-ad98-bbe63b910f77": "\"/providers/microsoft.powerapps/apis/shared_sharepointonline/connections/87492160903f4fda9a29d48e42c55ca1\""
  },
  "LocalDatabaseReferencesAsEmpty": false,
  "LocalResourceFileNames": {
    "logo": "0001.svg",
    "logo_单图标": "0002.svg"
  },
  "LocalResourceRootPaths": {
    "logo": "https://docserverpwaprodseas.blob.core.windows.net/6c1c921b-c19e-4347-b726-889d8babbb3c-1/resource/Assets0Images00001.svg?sv=2017-04-17&sr=b&sig=3QlNS%2Fen%2FRa7o91S7Ggc41Y8CPJU4ei9%2FnkLo5eWS58%3D&spr=https&se=2022-09-27T09%3A20%3A51Z&sp=r",
    "logo_单图标": "https://docserverpwaprodseas.blob.core.windows.net/6c1c921b-c19e-4347-b726-889d8babbb3c-1/resource/Assets0Images00002.svg?sv=2017-04-17&sr=b&sig=%2BrGP%2FJIsyAeZ8Q8KNguPMqXY7yPSD30rAoAHvbc7z7s%3D&spr=https&se=2022-09-27T09%3A20%3A51Z&sp=r"
  },
  "OrderComponentMetadata": {},
  "OrderComponentTemplate": {},
  "OrderDataSource": {
    "Approval_Table": 4,
    "ApprovalDetail_Table": 3,
    "ApprovalListCol": 19,
    "ComboBoxSample": 5,
    "ConfigurationInfo": 6,
    "CustomGallerySample": 7,
    "DataFlowActionCol": 20,
    "DataFlowActionCol2": 21,
    "DataFlowActionCol3": 22,
    "DataFlowActionCol4": 23,
    "DepartmentForm": 24,
    "DropDownSample": 8,
    "EditDetailUserAttachment": 25,
    "EditDetailUserAttachment2": 26,
    "EditDetailUserForm_1": 27,
    "EditDetailUserForm_2": 28,
    "EditUserAttachment": 29,
    "EditUserForm": 30,
    "FontSize": 31,
    "FormTableType": 9,
    "FromHistoryList": 32,
    "GenericFormList": 10,
    "GenericFormModel": 11,
    "GenericUploadAttachMentFile": 12,
    "ListboxSample": 13,
    "MyContacts": 14,
    "NewUserForm": 33,
    "Office365用户": 0,
    "RadioSample": 15,
    "SendAttachmentToGenericUploadAttachMentFile": 1,
    "SendAttachmentToUploadFlowAttachMent": 2,
    "TemplateFileList": 16,
    "UploadFlowAttachMent": 17,
    "UserInfo": 18
  },
  "OrderGroupControls": {
    "BtnDashedIcon": {
      "BtnDashed_5": 0,
      "Icon4_13": 1
    },
    "BtnDashedIcon_1": {
      "BtnDashed_7": 0,
      "Icon4_14": 1
    },
    "BtnDashedIcon_2": {
      "Button_large_16": 0,
      "Icon4_15": 1
    },
    "BtnDashedIcon_3": {
      "Button_large_18": 0,
      "Icon4_19": 1
    },
    "BtnDashedIcon_4": {
      "Button_large_19": 0,
      "Icon4_21": 1
    },
    "BtnDashedIcon_5": {
      "BtnDashed_8": 0,
      "Icon4_24": 1
    },
    "BtnDefaultIcon": {
      "BtnDefault_2": 0,
      "Icon4_8": 1
    },
    "BtnDefaultIcon_1": {
      "BtnDefault_3": 0,
      "Icon4_9": 1
    },
    "BtnDefaultIcon_2": {
      "BtnDefault_5": 0,
      "Icon4_23": 1
    },
    "BtnLgIcon": {
      "BtnPrimary_1": 0,
      "Icon4_6": 1
    },
    "BtnLgIcon_1": {
      "BtnPrimary_3": 0,
      "Icon4_7": 1
    },
    "BtnLgIcon_2": {
      "BtnPrimary_4": 0,
      "Icon4_22": 1
    },
    "BtnPrimaryLgIcon": {
      "BtnPrimaryLg_1": 0,
      "Icon4_16": 1
    },
    "BtnSecondIcon": {
      "BtnSecond_2": 0,
      "Icon4_10": 1
    },
    "BtnSecondIcon_1": {
      "BtnSecond_3": 0,
      "Icon4_11": 1
    },
    "BtnSecondIcon_2": {
      "BtnSecond_4": 0,
      "Icon4_12": 1
    },
    "Group1": {
      "DateBackground_2": 0,
      "DateLineLabel1_39": 3,
      "TemplateEndDate_1": 1,
      "TemplateStartDate_1": 2
    },
    "Group2_2": {
      "Button_large_17": 0,
      "Icon4_18": 1
    },
    "Group2_3": {
      "BtnDashedLg_2": 0,
      "Icon4_20": 1
    },
    "SubmitViewGroup": {
      "BackgroundRectangle_6": 0,
      "SubmitViewfillinBtn_6": 3,
      "SubmitViewInfo_6": 4,
      "SubmitViewRectangle_6": 1,
      "SubmitViewsubmitBtn_6": 2
    }
  },
  "OrderPcfTemplate": {},
  "OrderTemplate": {},
  "OrderXMLTemplate": {
    "attachments": 11,
    "button": 4,
    "checkbox": 8,
    "circle": 7,
    "combobox": 9,
    "datepicker": 14,
    "dropdown": 12,
    "fluidGrid": 13,
    "gallery": 6,
    "groupContainer": 0,
    "icon": 1,
    "image": 2,
    "label": 3,
    "radio": 16,
    "rectangle": 10,
    "text": 5,
    "toggleSwitch": 15
  },
  "PublishOrderIndices": {
    "ActionFlowGallery": 578,
    "AlertInfoContainer": 382,
    "AlertInfoContainer_1": 386,
    "AlertInfoContainerSmall": 380,
    "AlertInfoContainerSmall_1": 384,
    "AlertSuccessContainer": 381,
    "AlertSuccessContainer_1": 385,
    "AlertSuccessContainerSmall": 379,
    "AlertSuccessContainerSmall_1": 383,
    "App": 0,
    "Attachment_Excel": 84,
    "Attachment_Excel2": 540,
    "Attachment_Zip": 96,
    "Attachment_Zip2": 557,
    "BackgroundRectangle_6": 16,
    "BottomContainer": 22,
    "BottomContainer_2": 453,
    "BtnDashed": 271,
    "BtnDashed_1": 294,
    "BtnDashed_2": 319,
    "BtnDashed_3": 280,
    "BtnDashed_4": 257,
    "BtnDashed_5": 272,
    "BtnDashed_6": 303,
    "BtnDashed_7": 295,
    "BtnDashed_8": 320,
    "BtnDashedIcon": 328,
    "BtnDashedIcon_1": 338,
    "BtnDashedIcon_2": 329,
    "BtnDashedIcon_3": 334,
    "BtnDashedIcon_4": 339,
    "BtnDashedIcon_5": 342,
    "BtnDashedIconOnly": 273,
    "BtnDashedIconOnly_1": 296,
    "BtnDashedIconOnly_2": 282,
    "BtnDashedIconOnly_3": 259,
    "BtnDashedIconOnly_4": 305,
    "BtnDashedIconOnly_5": 321,
    "BtnDashedLg_1": 240,
    "BtnDashedLg_2": 241,
    "BtnDashedLgIconOnly": 242,
    "BtnDefault": 268,
    "BtnDefault_1": 291,
    "BtnDefault_17": 149,
    "BtnDefault_18": 118,
    "BtnDefault_19": 596,
    "BtnDefault_2": 269,
    "BtnDefault_20": 505,
    "BtnDefault_21": 506,
    "BtnDefault_22": 507,
    "BtnDefault_23": 61,
    "BtnDefault_24": 62,
    "BtnDefault_25": 63,
    "BtnDefault_26": 127,
    "BtnDefault_27": 136,
    "BtnDefault_3": 292,
    "BtnDefault_4": 316,
    "BtnDefault_5": 317,
    "BtnDefaultIcon": 326,
    "BtnDefaultIcon_1": 336,
    "BtnDefaultIcon_2": 341,
    "BtnDefaultIconOnly": 270,
    "BtnDefaultIconOnly_1": 293,
    "BtnDefaultIconOnly_2": 318,
    "BtnDefaultIconOnly_3": 545,
    "BtnDefaultLg": 245,
    "BtnDefaultLg_12": 55,
    "BtnDefaultLg_13": 498,
    "BtnDefaultLg_6": 156,
    "BtnDefaultLg_7": 604,
    "BtnDefaultLg_8": 605,
    "BtnDefaultLg_9": 12,
    "BtnLgIcon": 325,
    "BtnLgIcon_1": 335,
    "BtnLgIcon_2": 340,
    "BtnLgIconOnly": 267,
    "BtnLgIconOnly_1": 290,
    "BtnLgIconOnly_2": 315,
    "BtnLink": 263,
    "BtnLink_1": 287,
    "BtnLink_2": 311,
    "BtnLink_3": 402,
    "BtnLink_4": 403,
    "BtnLinkLg": 250,
    "BtnPrimary": 265,
    "BtnPrimary_1": 266,
    "BtnPrimary_2": 313,
    "BtnPrimary_3": 289,
    "BtnPrimary_4": 314,
    "BtnPrimaryLg": 239,
    "BtnPrimaryLg_1": 243,
    "BtnPrimaryLg_10": 607,
    "BtnPrimaryLg_12": 54,
    "BtnPrimaryLg_13": 497,
    "BtnPrimaryLg_7": 157,
    "BtnPrimaryLg_8": 606,
    "BtnPrimaryLg_9": 11,
    "BtnPrimaryLgIcon": 330,
    "BtnPrimaryLgIconOnly": 244,
    "BtnPrimarySmall_2": 288,
    "BtnSecond": 277,
    "BtnSecond_1": 300,
    "BtnSecond_2": 278,
    "BtnSecond_3": 255,
    "BtnSecond_4": 301,
    "BtnSecondIcon": 327,
    "BtnSecondIcon_1": 333,
    "BtnSecondIcon_2": 337,
    "BtnSecondIconOnly": 279,
    "BtnSecondIconOnly_1": 256,
    "BtnSecondIconOnly_17": 151,
    "BtnSecondIconOnly_18": 598,
    "BtnSecondIconOnly_19": 120,
    "BtnSecondIconOnly_2": 302,
    "BtnSecondIconOnly_21": 44,
    "BtnSecondIconOnly_22": 129,
    "BtnSecondIconOnly_23": 481,
    "BtnSecondIconOnly_25": 138,
    "BtnSecondIconOnly_26": 461,
    "BtnText": 262,
    "BtnText_1": 286,
    "BtnTextLg": 249,
    "Button_large_10": 254,
    "Button_large_16": 281,
    "Button_large_17": 246,
    "Button_large_18": 258,
    "Button_large_19": 304,
    "canDesignGuide": 159,
    "Checkbox2": 362,
    "Checkbox2_1": 52,
    "Checkbox2_2": 39,
    "Checkbox2_3": 495,
    "Checkbox2_4": 489,
    "Circle1_4": 50,
    "Circle1_5": 37,
    "Circle1_6": 493,
    "Circle1_7": 487,
    "Circle2_10": 115,
    "Circle2_11": 586,
    "Circle2_12": 124,
    "Circle2_13": 133,
    "Circle2_14": 581,
    "Circle2_7": 146,
    "Circle2_8": 142,
    "Circle2_9": 593,
    "ComboBox1": 351,
    "ComboBox1_11": 153,
    "ComboBox1_12": 600,
    "ComboBox1_13": 122,
    "ComboBox1_14": 131,
    "ComboBox1_15": 140,
    "ComboBox1_5": 31,
    "ComboBox1_6": 473,
    "CommentLabel_1": 589,
    "CommentLabel_2": 590,
    "CommentsContainer": 81,
    "CommentsContainer_1": 535,
    "CompleteScreen": 2,
    "Container1": 85,
    "Container10_1": 452,
    "Container11_1": 155,
    "Container11_2": 602,
    "Container11_5": 34,
    "Container11_6": 477,
    "Container12": 537,
    "Container12_2": 539,
    "Container12_3": 83,
    "Container13": 544,
    "Container13_10": 66,
    "Container13_11": 67,
    "Container13_12": 509,
    "Container13_13": 510,
    "Container13_14": 511,
    "Container13_15": 512,
    "Container13_16": 513,
    "Container13_17": 514,
    "Container13_18": 515,
    "Container13_8": 64,
    "Container13_9": 65,
    "Container16_10": 457,
    "Container16_4": 27,
    "Container16_5": 28,
    "Container16_6": 470,
    "Container16_7": 471,
    "Container17_2": 30,
    "Container17_3": 472,
    "Container17_5": 458,
    "Container2": 376,
    "Container3": 98,
    "Container4": 4,
    "Container5": 95,
    "Container6": 541,
    "Container7": 558,
    "Container8": 82,
    "Container9": 538,
    "CopyIcon_3": 591,
    "CountDepartment": 42,
    "CountDepartment_1": 480,
    "CountLast": 41,
    "CountLast_1": 479,
    "crdButton": 161,
    "crdColor": 160,
    "crdComponent": 162,
    "crdFont": 163,
    "CreateGeneralFormScreen": 13,
    "DataCardValue2": 366,
    "DateBackground_2": 357,
    "DateLineLabel1_39": 361,
    "DatePicker1": 352,
    "Design elements": 164,
    "Design Guide Screen": 158,
    "DetailGeneralFormScreen": 448,
    "DownloadIcon_1": 564,
    "DownloadIcon_2": 548,
    "DownloadIcon_6": 464,
    "Dropdown1": 350,
    "Dropdown1_5": 147,
    "Dropdown1_6": 594,
    "Dropdown1_7": 116,
    "Dropdown1_8": 125,
    "Dropdown1_9": 134,
    "drpFilterDepartment_1": 88,
    "FileLabel_1": 566,
    "FileLabel_2": 547,
    "FileLabel_6": 465,
    "FillInContainer": 57,
    "FillInContainer_1": 500,
    "FilterLabelContainer": 80,
    "FilterLabelContainer_1": 534,
    "FlowActionStepContainer": 576,
    "FormNameContainer": 58,
    "FormNameContainer_1": 501,
    "FormNameLabel_1": 60,
    "FormNameLabel_2": 504,
    "FormNameLabel_5": 43,
    "FormNameLabel_6": 478,
    "FormNameLabel_8": 460,
    "Gallery_FormHistory_3": 459,
    "Gallery2_2": 33,
    "Gallery2_3": 29,
    "Gallery2_4": 476,
    "Gallery2_5": 475,
    "Gallery4": 377,
    "Gallery4_1": 439,
    "Gallery6_3": 556,
    "galleryTemplate1_2": 48,
    "galleryTemplate1_3": 35,
    "galleryTemplate1_4": 491,
    "galleryTemplate1_5": 485,
    "galleryTemplate2": 584,
    "galleryTemplate3": 389,
    "galleryTemplate3_1": 392,
    "galleryTemplate3_5": 45,
    "galleryTemplate3_6": 482,
    "galleryTemplate4": 398,
    "galleryTemplate4_1": 444,
    "galleryTemplate8_3": 560,
    "galleryTemplate8_7": 462,
    "GeneralFlowContainer": 113,
    "Group1": 388,
    "Group2_2": 331,
    "Group2_3": 332,
    "HeaderContainer_2": 449,
    "HeaderContainer_3": 3,
    "HeaderContainer_4": 14,
    "Hide_Pwd": 551,
    "Hide_Pwd_1": 563,
    "Hide_Pwd_5": 469,
    "HistoryContainer": 450,
    "Icon2_4": 454,
    "Icon2_5": 6,
    "Icon2_6": 24,
    "Icon3": 9,
    "Icon4_10": 283,
    "Icon4_11": 260,
    "Icon4_12": 306,
    "Icon4_13": 276,
    "Icon4_14": 299,
    "Icon4_15": 284,
    "Icon4_16": 252,
    "Icon4_17": 247,
    "Icon4_18": 253,
    "Icon4_19": 261,
    "Icon4_20": 251,
    "Icon4_21": 307,
    "Icon4_22": 322,
    "Icon4_23": 323,
    "Icon4_24": 324,
    "Icon4_30": 411,
    "Icon4_31": 415,
    "Icon4_32": 405,
    "Icon4_33": 408,
    "Icon4_34": 425,
    "Icon4_35": 419,
    "Icon4_36": 429,
    "Icon4_37": 422,
    "Icon4_6": 274,
    "Icon4_7": 297,
    "Icon4_8": 275,
    "Icon4_9": 298,
    "Icon5_2": 51,
    "Icon5_3": 38,
    "Icon5_4": 494,
    "Icon5_5": 488,
    "iconSuccess": 412,
    "iconSuccess_1": 416,
    "iconSuccess_2": 426,
    "iconSuccess_3": 430,
    "iconSuccess4": 407,
    "iconSuccess4_1": 410,
    "iconSuccess4_2": 421,
    "iconSuccess4_3": 424,
    "Image1": 455,
    "Image1_1": 25,
    "Image1_2": 7,
    "Image2": 536,
    "Image3": 559,
    "Image3_13": 466,
    "Image3_8": 567,
    "Image3_9": 546,
    "Image4_1": 97,
    "Image4_2": 89,
    "InfoContainer": 56,
    "InfoContainer_1": 499,
    "InfoContainer12_2": 59,
    "InfoContainer12_3": 502,
    "labColorCode": 189,
    "labColorCode_1": 198,
    "labColorCode_10": 215,
    "labColorCode_11": 218,
    "labColorCode_12": 221,
    "labColorCode_13": 224,
    "labColorCode_14": 227,
    "labColorCode_2": 207,
    "labColorCode_3": 190,
    "labColorCode_4": 199,
    "labColorCode_5": 208,
    "labColorCode_6": 214,
    "labColorCode_7": 191,
    "labColorCode_8": 200,
    "labColorCode_9": 209,
    "labColorName_1": 186,
    "labColorName_10": 206,
    "labColorName_11": 213,
    "labColorName_12": 217,
    "labColorName_13": 220,
    "labColorName_14": 223,
    "labColorName_15": 226,
    "labColorName_2": 195,
    "labColorName_3": 204,
    "labColorName_4": 187,
    "labColorName_5": 196,
    "labColorName_6": 205,
    "labColorName_7": 212,
    "labColorName_8": 188,
    "labColorName_9": 197,
    "Label1": 10,
    "Label1_1": 181,
    "Label1_10": 347,
    "Label1_11": 348,
    "Label1_12": 353,
    "Label1_129": 68,
    "Label1_13": 234,
    "Label1_130": 69,
    "Label1_131": 70,
    "Label1_132": 71,
    "Label1_133": 72,
    "Label1_134": 73,
    "Label1_135": 74,
    "Label1_136": 75,
    "Label1_137": 150,
    "Label1_138": 597,
    "Label1_139": 516,
    "Label1_14": 235,
    "Label1_140": 517,
    "Label1_141": 518,
    "Label1_142": 519,
    "Label1_143": 520,
    "Label1_144": 521,
    "Label1_145": 522,
    "Label1_146": 523,
    "Label1_147": 524,
    "Label1_148": 525,
    "Label1_149": 526,
    "Label1_15": 309,
    "Label1_150": 527,
    "Label1_151": 528,
    "Label1_152": 529,
    "Label1_153": 119,
    "Label1_154": 128,
    "Label1_155": 137,
    "Label1_16": 310,
    "Label1_17": 312,
    "Label1_18": 236,
    "Label1_19": 237,
    "Label1_2": 180,
    "Label1_20": 238,
    "Label1_21": 232,
    "Label1_22": 233,
    "Label1_23": 230,
    "Label1_24": 231,
    "Label1_25": 173,
    "Label1_26": 171,
    "Label1_27": 354,
    "Label1_28": 355,
    "Label1_29": 356,
    "Label1_3": 229,
    "Label1_30": 364,
    "Label1_31": 365,
    "Label1_32": 369,
    "Label1_33": 174,
    "Label1_34": 167,
    "Label1_35": 169,
    "Label1_36": 172,
    "Label1_37": 170,
    "Label1_38": 175,
    "Label1_39": 177,
    "Label1_4": 248,
    "Label1_40": 176,
    "Label1_41": 182,
    "Label1_42": 178,
    "Label1_43": 179,
    "Label1_44": 165,
    "Label1_45": 375,
    "Label1_46": 434,
    "Label1_47": 435,
    "Label1_48": 443,
    "Label1_49": 437,
    "Label1_5": 264,
    "Label1_50": 438,
    "Label1_51": 378,
    "Label1_52": 441,
    "Label1_53": 442,
    "Label1_54": 387,
    "Label1_6": 285,
    "Label1_7": 344,
    "Label1_73": 456,
    "Label1_74": 26,
    "Label1_75": 8,
    "Label1_8": 345,
    "Label1_9": 346,
    "Label10": 413,
    "Label10_1": 414,
    "Label10_10": 432,
    "Label10_11": 423,
    "Label10_2": 406,
    "Label10_3": 417,
    "Label10_4": 418,
    "Label10_5": 409,
    "Label10_6": 427,
    "Label10_7": 428,
    "Label10_8": 420,
    "Label10_9": 431,
    "Label12_7": 543,
    "Label2": 390,
    "Label2_1": 393,
    "Label2_5": 46,
    "Label2_6": 483,
    "Label3": 399,
    "Label3_1": 400,
    "Label3_2": 446,
    "Label3_3": 445,
    "Label4": 395,
    "Label4_1": 396,
    "Label4_2": 397,
    "Label5": 503,
    "Label6": 92,
    "Label6_1": 101,
    "Label6_17": 145,
    "Label6_18": 148,
    "Label6_19": 152,
    "Label6_2": 552,
    "Label6_20": 141,
    "Label6_21": 144,
    "Label6_22": 592,
    "Label6_23": 595,
    "Label6_24": 599,
    "Label6_25": 114,
    "Label6_26": 117,
    "Label6_27": 585,
    "Label6_28": 588,
    "Label6_29": 121,
    "Label6_3": 568,
    "Label6_30": 123,
    "Label6_31": 126,
    "Label6_32": 130,
    "Label6_33": 132,
    "Label6_34": 580,
    "Label6_35": 135,
    "Label6_36": 583,
    "Label6_39": 139,
    "Label6_4": 86,
    "Label6_5": 90,
    "Label6_6": 99,
    "Label7_10": 486,
    "Label7_11": 490,
    "Label7_4": 49,
    "Label7_5": 53,
    "Label7_6": 36,
    "Label7_7": 40,
    "Label7_8": 492,
    "Label7_9": 496,
    "Label9_22": 100,
    "Label9_23": 104,
    "Label9_24": 106,
    "Label9_25": 111,
    "Label9_26": 542,
    "Label9_27": 555,
    "Label9_28": 572,
    "Label9_29": 573,
    "Label9_30": 577,
    "Label9_31": 574,
    "Label9_33": 91,
    "Label9_34": 87,
    "lblTag": 370,
    "lblTag_1": 401,
    "lblTag_2": 371,
    "lblTag_3": 372,
    "lblTag_4": 373,
    "lblTag_5": 374,
    "LeftContainer12": 76,
    "LeftContainer12_1": 530,
    "LineRectangle_5": 154,
    "LineRectangle_6": 601,
    "MainflowContainer": 17,
    "NextStepContainer_1": 579,
    "PredefinedFlowContainer": 110,
    "Radio1": 363,
    "Rectangle1": 343,
    "Rectangle1_1": 308,
    "Rectangle1_2": 168,
    "Rectangle1_3": 166,
    "Rectangle1_4": 228,
    "Rectangle1_5": 433,
    "Rectangle2": 391,
    "Rectangle2_1": 394,
    "Rectangle2_5": 47,
    "Rectangle2_6": 484,
    "Rectangle3": 404,
    "Rectangle3_1": 447,
    "Rectangle4": 436,
    "Rectangle5_4": 143,
    "Rectangle5_6": 587,
    "Rectangle5_7": 582,
    "RightContainer": 77,
    "RightContainer_1": 531,
    "SampleFlowContainer": 108,
    "SelectUserContainer_2": 15,
    "SelectUserContainer_3": 451,
    "Show_Pwd": 550,
    "Show_Pwd_1": 562,
    "Show_Pwd_5": 468,
    "shpColor_1": 192,
    "shpColor_10": 211,
    "shpColor_11": 216,
    "shpColor_12": 219,
    "shpColor_13": 222,
    "shpColor_14": 225,
    "shpColor_15": 183,
    "shpColor_2": 184,
    "shpColor_3": 201,
    "shpColor_4": 193,
    "shpColor_5": 202,
    "shpColor_6": 210,
    "shpColor_7": 185,
    "shpColor_8": 194,
    "shpColor_9": 203,
    "StartFlowContainer": 112,
    "StartFlowContainer_1": 575,
    "Statuslbl": 508,
    "SubmitViewfillinBtn_6": 20,
    "SubmitViewGroup": 23,
    "SubmitViewInfo_6": 19,
    "SubmitViewRectangle_6": 18,
    "SubmitViewsubmitBtn_6": 21,
    "TabGallery3": 367,
    "TabGallery3_1": 368,
    "TabGallery3_5": 32,
    "TabGallery3_6": 474,
    "TemplateContainer": 109,
    "TemplateEndDate_1": 359,
    "TemplateStartDate_1": 358,
    "TextInput_FilterLabel": 105,
    "TextInput_FilterLabel_1": 571,
    "TextInput_FormMark": 107,
    "TextInput_FormPWD": 93,
    "TextInput_FormPWD_1": 94,
    "TextInput_zipPWD": 102,
    "TextInput_zipPWD_1": 103,
    "TextInput1": 5,
    "TextInput2": 349,
    "TextInput2_1": 440,
    "TextInput2_30": 553,
    "TextInput2_31": 569,
    "TextInput2_32": 549,
    "TextInput2_33": 565,
    "TextInput2_34": 603,
    "TextInput2_35": 554,
    "TextInput2_37": 570,
    "TextInput2_39": 467,
    "Toggle1": 360,
    "UploadAttachmentsContainer": 79,
    "UploadAttachmentsContainer_1": 533,
    "UploaderLabel_1": 561,
    "UploaderLabel_5": 463,
    "UploadTemplateContainer": 78,
    "UploadTemplateContainer_1": 532
  },
  "ResourcesJsonIndices": {
    "Image-logo": 1,
    "Image-logo_单图标": 2,
    "Image-SampleImage": 0
  },
  "RuleScreenIdWithoutScreen": {},
  "TemplateVersions": {},
  "VolatileProperties": {
    "AnalysisLoadTime": 7.7891662,
    "ControlCount": {
      "attachments": 5,
      "button": 70,
      "checkbox": 5,
      "circle": 12,
      "combobox": 9,
      "dataCard": 4,
      "datepicker": 3,
      "dropdown": 6,
      "fluidGrid": 1,
      "gallery": 13,
      "galleryTemplate": 13,
      "group": 20,
      "groupContainer": 82,
      "icon": 79,
      "image": 10,
      "label": 214,
      "radio": 1,
      "rectangle": 35,
      "screen": 4,
      "text": 19,
      "toggleSwitch": 1
    },
    "DeserializationLoadTime": 15.4752759,
    "ErrorCount": 28
  },
  "WasLocalDatabaseReferencesEmpty": true
}