{
  "ComponentIndexes": {},
  "ControlUniqueGuids": {},
  "ControlUniqueIds": {
    "AlertInfoContainer": 263,
    "AlertInfoContainer_1": 281,
    "AlertInfoContainerSmall": 254,
    "AlertInfoContainerSmall_1": 272,
    "AlertSuccessContainer": 258,
    "AlertSuccessContainer_1": 276,
    "AlertSuccessContainerSmall": 250,
    "AlertSuccessContainerSmall_1": 268,
    "App": 1,
    "Attachment_Excel": 356,
    "Attachment_Excel2": 510,
    "Attachment_Zip": 362,
    "Attachment_Zip2": 525,
    "BottomContainer": 421,
    "BottomContainer_2": 562,
    "BtnDashed": 125,
    "BtnDashed_1": 148,
    "BtnDashed_2": 173,
    "BtnDashed_3": 134,
    "BtnDashed_4": 111,
    "BtnDashed_5": 126,
    "BtnDashed_6": 157,
    "BtnDashed_7": 149,
    "BtnDashed_8": 174,
    "BtnDashedIcon": 182,
    "BtnDashedIcon_1": 192,
    "BtnDashedIcon_2": 183,
    "BtnDashedIcon_3": 188,
    "BtnDashedIcon_4": 193,
    "BtnDashedIcon_5": 196,
    "BtnDashedIconOnly": 127,
    "BtnDashedIconOnly_1": 150,
    "BtnDashedIconOnly_2": 136,
    "BtnDashedIconOnly_3": 113,
    "BtnDashedIconOnly_4": 159,
    "BtnDashedIconOnly_5": 175,
    "BtnDashedLg_1": 94,
    "BtnDashedLg_2": 95,
    "BtnDashedLgIconOnly": 96,
    "BtnDefault": 122,
    "BtnDefault_1": 145,
    "BtnDefault_17": 405,
    "BtnDefault_18": 379,
    "BtnDefault_19": 557,
    "BtnDefault_2": 123,
    "BtnDefault_20": 497,
    "BtnDefault_21": 498,
    "BtnDefault_22": 499,
    "BtnDefault_23": 353,
    "BtnDefault_24": 354,
    "BtnDefault_25": 355,
    "BtnDefault_26": 389,
    "BtnDefault_28": 584,
    "BtnDefault_3": 146,
    "BtnDefault_4": 170,
    "BtnDefault_5": 171,
    "BtnDefaultIcon": 180,
    "BtnDefaultIcon_1": 190,
    "BtnDefaultIcon_2": 195,
    "BtnDefaultIconOnly": 124,
    "BtnDefaultIconOnly_1": 147,
    "BtnDefaultIconOnly_2": 172,
    "BtnDefaultIconOnly_3": 509,
    "BtnDefaultLg": 99,
    "BtnDefaultLg_11": 450,
    "BtnDefaultLg_12": 328,
    "BtnDefaultLg_6": 424,
    "BtnDefaultLg_7": 566,
    "BtnDefaultLg_8": 567,
    "BtnDefaultLg_9": 12,
    "BtnLgIcon": 179,
    "BtnLgIcon_1": 189,
    "BtnLgIcon_2": 194,
    "BtnLgIconOnly": 121,
    "BtnLgIconOnly_1": 144,
    "BtnLgIconOnly_2": 169,
    "BtnLink": 117,
    "BtnLink_1": 141,
    "BtnLink_2": 165,
    "BtnLink_3": 246,
    "BtnLink_4": 247,
    "BtnLinkLg": 104,
    "BtnPrimary": 119,
    "BtnPrimary_1": 120,
    "BtnPrimary_2": 167,
    "BtnPrimary_3": 143,
    "BtnPrimary_4": 168,
    "BtnPrimaryLg": 93,
    "BtnPrimaryLg_1": 97,
    "BtnPrimaryLg_11": 449,
    "BtnPrimaryLg_12": 327,
    "BtnPrimaryLg_7": 425,
    "BtnPrimaryLg_8": 568,
    "BtnPrimaryLg_9": 11,
    "BtnPrimaryLgIcon": 184,
    "BtnPrimaryLgIconOnly": 98,
    "BtnPrimarySmall_2": 142,
    "BtnSecond": 131,
    "BtnSecond_1": 154,
    "BtnSecond_2": 132,
    "BtnSecond_3": 109,
    "BtnSecond_4": 155,
    "BtnSecondIcon": 181,
    "BtnSecondIcon_1": 187,
    "BtnSecondIcon_2": 191,
    "BtnSecondIconOnly": 133,
    "BtnSecondIconOnly_1": 110,
    "BtnSecondIconOnly_17": 407,
    "BtnSecondIconOnly_18": 559,
    "BtnSecondIconOnly_19": 381,
    "BtnSecondIconOnly_2": 156,
    "BtnSecondIconOnly_20": 436,
    "BtnSecondIconOnly_21": 314,
    "BtnSecondIconOnly_22": 391,
    "BtnSecondIconOnly_24": 590,
    "BtnText": 116,
    "BtnText_1": 140,
    "BtnTextLg": 103,
    "Button_large_10": 108,
    "Button_large_16": 135,
    "Button_large_17": 100,
    "Button_large_18": 112,
    "Button_large_19": 158,
    "canDesignGuide": 15,
    "Checkbox2": 217,
    "Circle1_3": 445,
    "Circle1_4": 323,
    "Circle2_10": 376,
    "Circle2_11": 546,
    "Circle2_12": 386,
    "Circle2_14": 540,
    "Circle2_15": 583,
    "Circle2_7": 402,
    "Circle2_8": 397,
    "Circle2_9": 554,
    "ComboBox1": 206,
    "ComboBox1_11": 409,
    "ComboBox1_12": 561,
    "ComboBox1_13": 383,
    "ComboBox1_14": 393,
    "ComboBox1_16": 586,
    "ComboBox1_4": 437,
    "ComboBox1_5": 315,
    "CommentLabel_1": 549,
    "CommentLabel_2": 550,
    "CommentsContainer": 367,
    "CommentsContainer_1": 530,
    "CompleteScreen": 3,
    "Container1": 357,
    "Container10_1": 463,
    "Container11_1": 423,
    "Container11_2": 564,
    "Container11_4": 448,
    "Container11_5": 326,
    "Container12": 495,
    "Container12_2": 500,
    "Container12_3": 350,
    "Container13": 501,
    "Container13_10": 340,
    "Container13_11": 343,
    "Container13_12": 470,
    "Container13_13": 473,
    "Container13_14": 476,
    "Container13_15": 479,
    "Container13_16": 482,
    "Container13_17": 485,
    "Container13_18": 488,
    "Container13_8": 334,
    "Container13_9": 337,
    "Container16_2": 432,
    "Container16_3": 433,
    "Container16_4": 310,
    "Container16_5": 311,
    "Container17_1": 434,
    "Container17_2": 312,
    "Container2": 237,
    "Container3": 364,
    "Container4": 8,
    "Container6": 511,
    "Container7": 526,
    "CopyIcon_3": 551,
    "crdButton": 81,
    "crdColor": 16,
    "crdComponent": 197,
    "crdFont": 288,
    "CreateGeneralFormScreen": 304,
    "DataCardValue2": 221,
    "DateBackground_2": 212,
    "DateLineLabel1_39": 216,
    "DatePicker1": 207,
    "Design elements": 17,
    "Design Guide Screen": 14,
    "DetailGeneralFormScreen": 426,
    "DownloadIcon_1": 521,
    "DownloadIcon_2": 505,
    "DownloadIcon_3": 459,
    "Dropdown1": 205,
    "Dropdown1_5": 403,
    "Dropdown1_6": 555,
    "Dropdown1_7": 377,
    "Dropdown1_8": 387,
    "drpFilterDepartment_1": 349,
    "FileLabel_1": 523,
    "FileLabel_2": 503,
    "FileLabel_3": 458,
    "FillInContainer": 346,
    "FillInContainer_1": 491,
    "Form_history": 452,
    "FormHistoryContainer": 451,
    "FormNameContainer": 331,
    "FormNameContainer_1": 465,
    "FormNameLabel_1": 332,
    "FormNameLabel_2": 467,
    "FormNameLabel_4": 435,
    "FormNameLabel_5": 313,
    "Gallery_FormHistory": 454,
    "Gallery2_1": 442,
    "Gallery2_2": 320,
    "Gallery4": 241,
    "Gallery4_1": 295,
    "Gallery6_3": 516,
    "Gallery7": 543,
    "galleryTemplate1_1": 443,
    "galleryTemplate1_2": 321,
    "galleryTemplate2": 544,
    "galleryTemplate3": 223,
    "galleryTemplate3_1": 227,
    "galleryTemplate3_4": 439,
    "galleryTemplate3_5": 317,
    "galleryTemplate4": 242,
    "galleryTemplate4_1": 296,
    "galleryTemplate5": 571,
    "galleryTemplate8_3": 517,
    "galleryTemplate8_4": 455,
    "GeneralFlowContainer": 400,
    "Group1": 287,
    "Group2_2": 185,
    "Group2_3": 186,
    "HeaderContainer_2": 427,
    "HeaderContainer_3": 4,
    "HeaderContainer_4": 305,
    "Hide_Pwd": 508,
    "Hide_Pwd_1": 520,
    "Hide_Pwd_2": 462,
    "Icon1": 453,
    "Icon2_4": 428,
    "Icon2_5": 5,
    "Icon2_6": 306,
    "Icon3": 9,
    "Icon4_10": 137,
    "Icon4_11": 114,
    "Icon4_12": 160,
    "Icon4_13": 130,
    "Icon4_14": 153,
    "Icon4_15": 138,
    "Icon4_16": 106,
    "Icon4_17": 101,
    "Icon4_18": 107,
    "Icon4_19": 115,
    "Icon4_20": 105,
    "Icon4_21": 161,
    "Icon4_22": 176,
    "Icon4_23": 177,
    "Icon4_24": 178,
    "Icon4_30": 259,
    "Icon4_31": 264,
    "Icon4_32": 251,
    "Icon4_33": 255,
    "Icon4_34": 277,
    "Icon4_35": 269,
    "Icon4_36": 282,
    "Icon4_37": 273,
    "Icon4_6": 128,
    "Icon4_7": 151,
    "Icon4_8": 129,
    "Icon4_9": 152,
    "Icon5_1": 446,
    "Icon5_2": 324,
    "iconSuccess": 260,
    "iconSuccess_1": 265,
    "iconSuccess_2": 278,
    "iconSuccess_3": 283,
    "iconSuccess4": 253,
    "iconSuccess4_1": 257,
    "iconSuccess4_2": 271,
    "iconSuccess4_3": 275,
    "Image1": 429,
    "Image1_1": 307,
    "Image1_2": 6,
    "Image2": 494,
    "Image3": 529,
    "Image3_10": 457,
    "Image3_8": 524,
    "Image3_9": 504,
    "Image4_1": 363,
    "Image4_2": 351,
    "InfoContainer": 330,
    "InfoContainer_1": 464,
    "InfoContainer12_2": 333,
    "InfoContainer12_3": 469,
    "labColorCode": 42,
    "labColorCode_1": 51,
    "labColorCode_10": 68,
    "labColorCode_11": 71,
    "labColorCode_12": 74,
    "labColorCode_13": 77,
    "labColorCode_14": 80,
    "labColorCode_2": 60,
    "labColorCode_3": 43,
    "labColorCode_4": 52,
    "labColorCode_5": 61,
    "labColorCode_6": 67,
    "labColorCode_7": 44,
    "labColorCode_8": 53,
    "labColorCode_9": 62,
    "labColorName_1": 39,
    "labColorName_10": 59,
    "labColorName_11": 66,
    "labColorName_12": 70,
    "labColorName_13": 73,
    "labColorName_14": 76,
    "labColorName_15": 79,
    "labColorName_2": 48,
    "labColorName_3": 57,
    "labColorName_4": 40,
    "labColorName_5": 49,
    "labColorName_6": 58,
    "labColorName_7": 65,
    "labColorName_8": 41,
    "labColorName_9": 50,
    "Label1": 10,
    "Label1_1": 34,
    "Label1_10": 202,
    "Label1_11": 203,
    "Label1_12": 208,
    "Label1_129": 335,
    "Label1_13": 88,
    "Label1_130": 336,
    "Label1_131": 338,
    "Label1_132": 339,
    "Label1_133": 341,
    "Label1_134": 342,
    "Label1_135": 344,
    "Label1_136": 345,
    "Label1_137": 406,
    "Label1_138": 558,
    "Label1_139": 471,
    "Label1_14": 89,
    "Label1_140": 472,
    "Label1_141": 474,
    "Label1_142": 475,
    "Label1_143": 477,
    "Label1_144": 478,
    "Label1_145": 480,
    "Label1_146": 481,
    "Label1_147": 483,
    "Label1_148": 484,
    "Label1_149": 486,
    "Label1_15": 163,
    "Label1_150": 487,
    "Label1_151": 489,
    "Label1_152": 490,
    "Label1_153": 380,
    "Label1_154": 390,
    "Label1_156": 589,
    "Label1_16": 164,
    "Label1_17": 166,
    "Label1_18": 90,
    "Label1_19": 91,
    "Label1_2": 33,
    "Label1_20": 92,
    "Label1_21": 86,
    "Label1_22": 87,
    "Label1_23": 84,
    "Label1_24": 85,
    "Label1_25": 26,
    "Label1_26": 24,
    "Label1_27": 209,
    "Label1_28": 210,
    "Label1_29": 211,
    "Label1_3": 83,
    "Label1_30": 219,
    "Label1_31": 220,
    "Label1_32": 230,
    "Label1_33": 27,
    "Label1_34": 20,
    "Label1_35": 22,
    "Label1_36": 25,
    "Label1_37": 23,
    "Label1_38": 28,
    "Label1_39": 30,
    "Label1_4": 102,
    "Label1_40": 29,
    "Label1_41": 35,
    "Label1_42": 31,
    "Label1_43": 32,
    "Label1_44": 18,
    "Label1_45": 236,
    "Label1_46": 290,
    "Label1_47": 291,
    "Label1_48": 303,
    "Label1_49": 293,
    "Label1_5": 118,
    "Label1_50": 294,
    "Label1_51": 249,
    "Label1_52": 301,
    "Label1_53": 302,
    "Label1_54": 286,
    "Label1_6": 139,
    "Label1_7": 199,
    "Label1_73": 430,
    "Label1_74": 308,
    "Label1_75": 7,
    "Label1_8": 200,
    "Label1_9": 201,
    "Label10": 261,
    "Label10_1": 262,
    "Label10_10": 285,
    "Label10_11": 274,
    "Label10_2": 252,
    "Label10_3": 266,
    "Label10_4": 267,
    "Label10_5": 256,
    "Label10_6": 279,
    "Label10_7": 280,
    "Label10_8": 270,
    "Label10_9": 284,
    "Label12_7": 502,
    "Label2": 224,
    "Label2_1": 228,
    "Label2_4": 440,
    "Label2_5": 318,
    "Label3": 243,
    "Label3_1": 244,
    "Label3_2": 298,
    "Label3_3": 297,
    "Label4": 238,
    "Label4_1": 239,
    "Label4_2": 240,
    "Label5": 466,
    "Label6": 358,
    "Label6_1": 365,
    "Label6_17": 401,
    "Label6_18": 404,
    "Label6_19": 408,
    "Label6_2": 512,
    "Label6_20": 396,
    "Label6_21": 399,
    "Label6_22": 553,
    "Label6_23": 556,
    "Label6_24": 560,
    "Label6_25": 375,
    "Label6_26": 378,
    "Label6_27": 545,
    "Label6_28": 548,
    "Label6_29": 382,
    "Label6_3": 527,
    "Label6_30": 385,
    "Label6_31": 388,
    "Label6_32": 392,
    "Label6_34": 539,
    "Label6_36": 542,
    "Label6_37": 585,
    "Label6_38": 587,
    "Label7_2": 444,
    "Label7_3": 447,
    "Label7_4": 322,
    "Label7_5": 325,
    "Label9_22": 361,
    "Label9_23": 371,
    "Label9_24": 368,
    "Label9_25": 394,
    "Label9_26": 496,
    "Label9_27": 515,
    "Label9_28": 534,
    "Label9_29": 531,
    "Label9_30": 537,
    "Label9_31": 532,
    "Label9_32": 535,
    "Label9_33": 352,
    "lblTag": 231,
    "lblTag_1": 245,
    "lblTag_2": 232,
    "lblTag_3": 233,
    "lblTag_4": 234,
    "lblTag_5": 235,
    "LeftContainer12": 347,
    "LeftContainer12_1": 492,
    "LineRectangle_5": 422,
    "LineRectangle_6": 563,
    "MainflowContainer": 329,
    "NextStepContainer_1": 552,
    "PredefinedFlowContainer": 410,
    "PredefineFlowGallery": 570,
    "Radio1": 218,
    "Rectangle1": 198,
    "Rectangle1_1": 162,
    "Rectangle1_2": 21,
    "Rectangle1_3": 19,
    "Rectangle1_4": 82,
    "Rectangle1_5": 289,
    "Rectangle2": 225,
    "Rectangle2_1": 229,
    "Rectangle2_4": 441,
    "Rectangle2_5": 319,
    "Rectangle3": 248,
    "Rectangle3_1": 299,
    "Rectangle4": 292,
    "Rectangle5_4": 398,
    "Rectangle5_6": 547,
    "Rectangle5_7": 541,
    "Rectangle5_8": 588,
    "ReferNumContainer": 370,
    "ReferNumContainer_1": 533,
    "RightContainer": 373,
    "RightContainer_1": 536,
    "SampleFlowContainer": 374,
    "SelectUserContainer_1": 431,
    "SelectUserContainer_2": 309,
    "Show_Pwd": 507,
    "Show_Pwd_1": 519,
    "Show_Pwd_2": 461,
    "shpColor_1": 45,
    "shpColor_10": 64,
    "shpColor_11": 69,
    "shpColor_12": 72,
    "shpColor_13": 75,
    "shpColor_14": 78,
    "shpColor_15": 36,
    "shpColor_2": 37,
    "shpColor_3": 54,
    "shpColor_4": 46,
    "shpColor_5": 55,
    "shpColor_6": 63,
    "shpColor_7": 38,
    "shpColor_8": 47,
    "shpColor_9": 56,
    "StartFlowContainer": 395,
    "StartFlowContainer_1": 538,
    "Statuslbl": 468,
    "TabGallery3": 222,
    "TabGallery3_1": 226,
    "TabGallery3_4": 438,
    "TabGallery3_5": 316,
    "TemplateContainer": 384,
    "TemplateEndDate_1": 214,
    "TemplateStartDate_1": 213,
    "TextInput_FormMark": 369,
    "TextInput_FormPWD": 359,
    "TextInput_ReferNumber": 372,
    "TextInput_zipPWD": 366,
    "TextInput1": 13,
    "TextInput2": 204,
    "TextInput2_1": 300,
    "TextInput2_30": 513,
    "TextInput2_31": 528,
    "TextInput2_32": 506,
    "TextInput2_33": 522,
    "TextInput2_34": 565,
    "TextInput2_35": 460,
    "Toggle1": 215,
    "UploadAttachmentsContainer": 360,
    "UploadAttachmentsContainer_1": 514,
    "UploaderLabel_1": 518,
    "UploaderLabel_2": 456,
    "UploadTemplateContainer": 348,
    "UploadTemplateContainer_1": 493,
    "UserdisplayGroup_1": 591
  },
  "FunctionParamsInvariantScripts": {},
  "FunctionParamsInvariantScriptsOnInstances": {},
  "HeaderLastSavedDateTimeUTC": "08/18/2022 03:22:49",
  "IsLegacyComponentAllowGlobalScopeCase": false,
  "LocalConnectionIDReferences": {
    "7c4cb0cb-4057-4e8f-9e81-658856e779cf": "\"/providers/microsoft.powerapps/apis/shared_logicflows/connections/5b299dd21406477db12fe23343be43f3-7c7547c680553065\"",
    "d8c8758b-8da6-4da9-b896-855b4b1f6419": "\"/providers/microsoft.powerapps/apis/shared_logicflows/connections/f3b366c9-ae33-4e98-8f4c-db28ef3d9a2c\"",
    "ed5c50bd-bb07-4f5f-ad98-bbe63b910f77": "\"/providers/microsoft.powerapps/apis/shared_sharepointonline/connections/87492160903f4fda9a29d48e42c55ca1\""
  },
  "LocalDatabaseReferencesAsEmpty": false,
  "LocalResourceFileNames": {
    "logo": "8a96dd20-7821-4710-952b-f924d2e6e363.svg",
    "logo_单图标": "3f52ee81-97b1-4796-8e4d-4bd8e9ce3511.svg"
  },
  "LocalResourceRootPaths": {
    "logo": "https://docserverpwaprodseas.blob.core.windows.net/9e4efbb5-5a6e-4f2f-9bfc-80f3cab07d77-1/resource/Assets0Images08a96dd20-7821-4710-952b-f924d2e6e363.svg?sv=2017-04-17&sr=b&sig=RzS%2BtOTB1bmpC42lc8FikPj3nJckMa9OZHJW7kDQE0Q%3D&spr=https&se=2022-08-19T02%3A40%3A11Z&sp=r",
    "logo_单图标": "https://docserverpwaprodseas.blob.core.windows.net/9e4efbb5-5a6e-4f2f-9bfc-80f3cab07d77-1/resource/Assets0Images03f52ee81-97b1-4796-8e4d-4bd8e9ce3511.svg?sv=2017-04-17&sr=b&sig=W%2Bs4F%2BK5IL1DHZx1YsfW4I6ddt3dBDDJ2nGtX%2B6yy84%3D&spr=https&se=2022-08-19T02%3A40%3A11Z&sp=r"
  },
  "OrderComponentMetadata": {},
  "OrderComponentTemplate": {},
  "OrderDataSource": {
    "Approval_Table": 9,
    "ApprovalDetail_Table": 8,
    "ApprovalListCol": 27,
    "AttachmentExcelName": 20,
    "AttachmentZipName": 21,
    "ComboBoxSample": 3,
    "CustomGallerySample": 5,
    "DataFlowActionCol": 28,
    "DropDownSample": 2,
    "EditDetailUserAttachment": 23,
    "EditDetailUserAttachment2": 26,
    "EditDetailUserForm_1": 24,
    "EditDetailUserForm_2": 22,
    "EditUserAttachment": 18,
    "EditUserForm": 19,
    "FontSize": 17,
    "FormTableType": 16,
    "GenericFormList": 10,
    "GenericFormModel": 11,
    "GenericFormModel_1": 15,
    "GenericUploadAttachMentFile": 14,
    "ListboxSample": 6,
    "MyContacts": 7,
    "NewUserForm": 25,
    "RadioSample": 4,
    "SendAttachmentToGenericUploadAttachMentFile": 0,
    "SendAttachmentToUploadFlowAttachMent": 1,
    "TemplateFileList": 12,
    "UploadFlowAttachMent": 13
  },
  "OrderGroupControls": {
    "BtnDashedIcon": {
      "BtnDashed_5": 1,
      "Icon4_13": 0
    },
    "BtnDashedIcon_1": {
      "BtnDashed_7": 1,
      "Icon4_14": 0
    },
    "BtnDashedIcon_2": {
      "Button_large_16": 1,
      "Icon4_15": 0
    },
    "BtnDashedIcon_3": {
      "Button_large_18": 1,
      "Icon4_19": 0
    },
    "BtnDashedIcon_4": {
      "Button_large_19": 1,
      "Icon4_21": 0
    },
    "BtnDashedIcon_5": {
      "BtnDashed_8": 1,
      "Icon4_24": 0
    },
    "BtnDefaultIcon": {
      "BtnDefault_2": 1,
      "Icon4_8": 0
    },
    "BtnDefaultIcon_1": {
      "BtnDefault_3": 1,
      "Icon4_9": 0
    },
    "BtnDefaultIcon_2": {
      "BtnDefault_5": 1,
      "Icon4_23": 0
    },
    "BtnLgIcon": {
      "BtnPrimary_1": 1,
      "Icon4_6": 0
    },
    "BtnLgIcon_1": {
      "BtnPrimary_3": 1,
      "Icon4_7": 0
    },
    "BtnLgIcon_2": {
      "BtnPrimary_4": 1,
      "Icon4_22": 0
    },
    "BtnPrimaryLgIcon": {
      "BtnPrimaryLg_1": 1,
      "Icon4_16": 0
    },
    "BtnSecondIcon": {
      "BtnSecond_2": 1,
      "Icon4_10": 0
    },
    "BtnSecondIcon_1": {
      "BtnSecond_3": 1,
      "Icon4_11": 0
    },
    "BtnSecondIcon_2": {
      "BtnSecond_4": 1,
      "Icon4_12": 0
    },
    "Group1": {
      "DateBackground_2": 0,
      "DateLineLabel1_39": 3,
      "TemplateEndDate_1": 2,
      "TemplateStartDate_1": 1
    },
    "Group2_2": {
      "Button_large_17": 1,
      "Icon4_18": 0
    },
    "Group2_3": {
      "BtnDashedLg_2": 1,
      "Icon4_20": 0
    },
    "UserdisplayGroup_1": {
      "BtnSecondIconOnly_24": 1,
      "Label1_156": 0
    }
  },
  "OrderPcfTemplate": {},
  "OrderTemplate": {},
  "OrderXMLTemplate": {
    "attachments": 14,
    "button": 4,
    "checkbox": 12,
    "circle": 16,
    "combobox": 9,
    "datepicker": 10,
    "dropdown": 8,
    "fluidGrid": 6,
    "gallery": 15,
    "groupContainer": 0,
    "icon": 1,
    "image": 2,
    "label": 3,
    "radio": 13,
    "rectangle": 7,
    "text": 5,
    "toggleSwitch": 11
  },
  "PublishOrderIndices": {
    "AlertInfoContainer": 524,
    "AlertInfoContainer_1": 542,
    "AlertInfoContainerSmall": 515,
    "AlertInfoContainerSmall_1": 533,
    "AlertSuccessContainer": 519,
    "AlertSuccessContainer_1": 537,
    "AlertSuccessContainerSmall": 511,
    "AlertSuccessContainerSmall_1": 529,
    "App": 0,
    "Attachment_Excel": 51,
    "Attachment_Excel2": 222,
    "Attachment_Zip": 57,
    "Attachment_Zip2": 238,
    "BottomContainer": 128,
    "BottomContainer_2": 137,
    "BtnDashed": 403,
    "BtnDashed_1": 426,
    "BtnDashed_2": 451,
    "BtnDashed_3": 412,
    "BtnDashed_4": 389,
    "BtnDashed_5": 404,
    "BtnDashed_6": 435,
    "BtnDashed_7": 427,
    "BtnDashed_8": 452,
    "BtnDashedIcon": 355,
    "BtnDashedIcon_1": 350,
    "BtnDashedIcon_2": 353,
    "BtnDashedIcon_3": 346,
    "BtnDashedIcon_4": 351,
    "BtnDashedIcon_5": 344,
    "BtnDashedIconOnly": 405,
    "BtnDashedIconOnly_1": 428,
    "BtnDashedIconOnly_2": 414,
    "BtnDashedIconOnly_3": 391,
    "BtnDashedIconOnly_4": 437,
    "BtnDashedIconOnly_5": 453,
    "BtnDashedLg_1": 372,
    "BtnDashedLg_2": 373,
    "BtnDashedLgIconOnly": 374,
    "BtnDefault": 400,
    "BtnDefault_1": 423,
    "BtnDefault_17": 100,
    "BtnDefault_18": 74,
    "BtnDefault_19": 270,
    "BtnDefault_2": 401,
    "BtnDefault_20": 209,
    "BtnDefault_21": 210,
    "BtnDefault_22": 211,
    "BtnDefault_23": 48,
    "BtnDefault_24": 49,
    "BtnDefault_25": 50,
    "BtnDefault_26": 84,
    "BtnDefault_28": 125,
    "BtnDefault_3": 424,
    "BtnDefault_4": 448,
    "BtnDefault_5": 449,
    "BtnDefaultIcon": 359,
    "BtnDefaultIcon_1": 348,
    "BtnDefaultIcon_2": 343,
    "BtnDefaultIconOnly": 402,
    "BtnDefaultIconOnly_1": 425,
    "BtnDefaultIconOnly_2": 450,
    "BtnDefaultIconOnly_3": 221,
    "BtnDefaultLg": 377,
    "BtnDefaultLg_11": 163,
    "BtnDefaultLg_12": 23,
    "BtnDefaultLg_6": 131,
    "BtnDefaultLg_7": 141,
    "BtnDefaultLg_8": 142,
    "BtnDefaultLg_9": 572,
    "BtnLgIcon": 361,
    "BtnLgIcon_1": 347,
    "BtnLgIcon_2": 342,
    "BtnLgIconOnly": 399,
    "BtnLgIconOnly_1": 422,
    "BtnLgIconOnly_2": 447,
    "BtnLink": 395,
    "BtnLink_1": 419,
    "BtnLink_2": 443,
    "BtnLink_3": 507,
    "BtnLink_4": 508,
    "BtnLinkLg": 382,
    "BtnPrimary": 397,
    "BtnPrimary_1": 398,
    "BtnPrimary_2": 445,
    "BtnPrimary_3": 421,
    "BtnPrimary_4": 446,
    "BtnPrimaryLg": 371,
    "BtnPrimaryLg_1": 375,
    "BtnPrimaryLg_11": 162,
    "BtnPrimaryLg_12": 22,
    "BtnPrimaryLg_7": 132,
    "BtnPrimaryLg_8": 143,
    "BtnPrimaryLg_9": 571,
    "BtnPrimaryLgIcon": 352,
    "BtnPrimaryLgIconOnly": 376,
    "BtnPrimarySmall_2": 420,
    "BtnSecond": 409,
    "BtnSecond_1": 432,
    "BtnSecond_2": 410,
    "BtnSecond_3": 387,
    "BtnSecond_4": 433,
    "BtnSecondIcon": 360,
    "BtnSecondIcon_1": 345,
    "BtnSecondIcon_2": 349,
    "BtnSecondIconOnly": 411,
    "BtnSecondIconOnly_1": 388,
    "BtnSecondIconOnly_17": 102,
    "BtnSecondIconOnly_18": 272,
    "BtnSecondIconOnly_19": 76,
    "BtnSecondIconOnly_2": 434,
    "BtnSecondIconOnly_20": 149,
    "BtnSecondIconOnly_21": 9,
    "BtnSecondIconOnly_22": 86,
    "BtnSecondIconOnly_24": 124,
    "BtnText": 394,
    "BtnText_1": 418,
    "BtnTextLg": 381,
    "Button_large_10": 386,
    "Button_large_16": 413,
    "Button_large_17": 378,
    "Button_large_18": 390,
    "Button_large_19": 436,
    "canDesignGuide": 275,
    "Checkbox2": 478,
    "Circle1_3": 158,
    "Circle1_4": 18,
    "Circle2_10": 71,
    "Circle2_11": 259,
    "Circle2_12": 81,
    "Circle2_14": 253,
    "Circle2_15": 120,
    "Circle2_7": 97,
    "Circle2_8": 92,
    "Circle2_9": 267,
    "ComboBox1": 467,
    "ComboBox1_11": 104,
    "ComboBox1_12": 274,
    "ComboBox1_13": 78,
    "ComboBox1_14": 88,
    "ComboBox1_16": 127,
    "ComboBox1_4": 150,
    "ComboBox1_5": 10,
    "CommentLabel_1": 262,
    "CommentLabel_2": 263,
    "CommentsContainer": 62,
    "CommentsContainer_1": 243,
    "CompleteScreen": 0,
    "Container1": 52,
    "Container10_1": 176,
    "Container11_1": 130,
    "Container11_2": 139,
    "Container11_4": 161,
    "Container11_5": 21,
    "Container12": 207,
    "Container12_2": 212,
    "Container12_3": 45,
    "Container13": 213,
    "Container13_10": 35,
    "Container13_11": 38,
    "Container13_12": 183,
    "Container13_13": 186,
    "Container13_14": 189,
    "Container13_15": 192,
    "Container13_16": 195,
    "Container13_17": 198,
    "Container13_18": 201,
    "Container13_8": 29,
    "Container13_9": 32,
    "Container16_2": 145,
    "Container16_3": 146,
    "Container16_4": 5,
    "Container16_5": 6,
    "Container17_1": 147,
    "Container17_2": 7,
    "Container2": 498,
    "Container3": 59,
    "Container4": 568,
    "Container6": 223,
    "Container7": 239,
    "CopyIcon_3": 264,
    "crdButton": 341,
    "crdColor": 276,
    "crdComponent": 457,
    "crdFont": 548,
    "CreateGeneralFormScreen": 0,
    "DataCardValue2": 482,
    "DateBackground_2": 473,
    "DateLineLabel1_39": 477,
    "DatePicker1": 468,
    "Design elements": 277,
    "Design Guide Screen": 0,
    "DetailGeneralFormScreen": 0,
    "DownloadIcon_1": 234,
    "DownloadIcon_2": 217,
    "DownloadIcon_3": 172,
    "Dropdown1": 466,
    "Dropdown1_5": 98,
    "Dropdown1_6": 268,
    "Dropdown1_7": 72,
    "Dropdown1_8": 82,
    "drpFilterDepartment_1": 44,
    "FileLabel_1": 236,
    "FileLabel_2": 215,
    "FileLabel_3": 171,
    "FillInContainer": 41,
    "FillInContainer_1": 204,
    "Form_history": 165,
    "FormHistoryContainer": 164,
    "FormNameContainer": 26,
    "FormNameContainer_1": 178,
    "FormNameLabel_1": 27,
    "FormNameLabel_2": 179,
    "FormNameLabel_4": 148,
    "FormNameLabel_5": 8,
    "Gallery_FormHistory": 167,
    "Gallery2_1": 155,
    "Gallery2_2": 15,
    "Gallery4": 502,
    "Gallery4_1": 555,
    "Gallery6_3": 229,
    "Gallery7": 256,
    "galleryTemplate1_1": 156,
    "galleryTemplate1_2": 16,
    "galleryTemplate2": 257,
    "galleryTemplate3": 484,
    "galleryTemplate3_1": 488,
    "galleryTemplate3_4": 152,
    "galleryTemplate3_5": 12,
    "galleryTemplate4": 503,
    "galleryTemplate4_1": 556,
    "galleryTemplate5": 118,
    "galleryTemplate8_3": 230,
    "galleryTemplate8_4": 168,
    "GeneralFlowContainer": 95,
    "Group1": 460,
    "Group2_2": 354,
    "Group2_3": 356,
    "HeaderContainer_2": 133,
    "HeaderContainer_3": 564,
    "HeaderContainer_4": 0,
    "Hide_Pwd": 220,
    "Hide_Pwd_1": 233,
    "Hide_Pwd_2": 175,
    "Icon1": 166,
    "Icon2_4": 134,
    "Icon2_5": 565,
    "Icon2_6": 1,
    "Icon3": 569,
    "Icon4_10": 415,
    "Icon4_11": 392,
    "Icon4_12": 438,
    "Icon4_13": 408,
    "Icon4_14": 431,
    "Icon4_15": 416,
    "Icon4_16": 384,
    "Icon4_17": 379,
    "Icon4_18": 385,
    "Icon4_19": 393,
    "Icon4_20": 383,
    "Icon4_21": 439,
    "Icon4_22": 454,
    "Icon4_23": 455,
    "Icon4_24": 456,
    "Icon4_30": 520,
    "Icon4_31": 525,
    "Icon4_32": 512,
    "Icon4_33": 516,
    "Icon4_34": 538,
    "Icon4_35": 530,
    "Icon4_36": 543,
    "Icon4_37": 534,
    "Icon4_6": 406,
    "Icon4_7": 429,
    "Icon4_8": 407,
    "Icon4_9": 430,
    "Icon5_1": 159,
    "Icon5_2": 19,
    "iconSuccess": 521,
    "iconSuccess_1": 526,
    "iconSuccess_2": 539,
    "iconSuccess_3": 544,
    "iconSuccess4": 514,
    "iconSuccess4_1": 518,
    "iconSuccess4_2": 532,
    "iconSuccess4_3": 536,
    "Image1": 135,
    "Image1_1": 2,
    "Image1_2": 566,
    "Image2": 226,
    "Image3": 242,
    "Image3_10": 170,
    "Image3_8": 237,
    "Image3_9": 216,
    "Image4_1": 58,
    "Image4_2": 46,
    "InfoContainer": 25,
    "InfoContainer_1": 177,
    "InfoContainer12_2": 28,
    "InfoContainer12_3": 182,
    "labColorCode": 302,
    "labColorCode_1": 311,
    "labColorCode_10": 328,
    "labColorCode_11": 331,
    "labColorCode_12": 334,
    "labColorCode_13": 337,
    "labColorCode_14": 340,
    "labColorCode_2": 320,
    "labColorCode_3": 303,
    "labColorCode_4": 312,
    "labColorCode_5": 321,
    "labColorCode_6": 327,
    "labColorCode_7": 304,
    "labColorCode_8": 313,
    "labColorCode_9": 322,
    "labColorName_1": 299,
    "labColorName_10": 319,
    "labColorName_11": 326,
    "labColorName_12": 330,
    "labColorName_13": 333,
    "labColorName_14": 336,
    "labColorName_15": 339,
    "labColorName_2": 308,
    "labColorName_3": 317,
    "labColorName_4": 300,
    "labColorName_5": 309,
    "labColorName_6": 318,
    "labColorName_7": 325,
    "labColorName_8": 301,
    "labColorName_9": 310,
    "Label1": 570,
    "Label1_1": 294,
    "Label1_10": 463,
    "Label1_11": 464,
    "Label1_12": 469,
    "Label1_129": 30,
    "Label1_13": 366,
    "Label1_130": 31,
    "Label1_131": 33,
    "Label1_132": 34,
    "Label1_133": 36,
    "Label1_134": 37,
    "Label1_135": 39,
    "Label1_136": 40,
    "Label1_137": 101,
    "Label1_138": 271,
    "Label1_139": 184,
    "Label1_14": 367,
    "Label1_140": 185,
    "Label1_141": 187,
    "Label1_142": 188,
    "Label1_143": 190,
    "Label1_144": 191,
    "Label1_145": 193,
    "Label1_146": 194,
    "Label1_147": 196,
    "Label1_148": 197,
    "Label1_149": 199,
    "Label1_15": 441,
    "Label1_150": 200,
    "Label1_151": 202,
    "Label1_152": 203,
    "Label1_153": 75,
    "Label1_154": 85,
    "Label1_156": 122,
    "Label1_16": 442,
    "Label1_17": 444,
    "Label1_18": 368,
    "Label1_19": 369,
    "Label1_2": 293,
    "Label1_20": 370,
    "Label1_21": 364,
    "Label1_22": 365,
    "Label1_23": 362,
    "Label1_24": 363,
    "Label1_25": 286,
    "Label1_26": 284,
    "Label1_27": 470,
    "Label1_28": 471,
    "Label1_29": 472,
    "Label1_3": 358,
    "Label1_30": 480,
    "Label1_31": 481,
    "Label1_32": 491,
    "Label1_33": 287,
    "Label1_34": 280,
    "Label1_35": 282,
    "Label1_36": 285,
    "Label1_37": 283,
    "Label1_38": 288,
    "Label1_39": 290,
    "Label1_4": 380,
    "Label1_40": 289,
    "Label1_41": 295,
    "Label1_42": 291,
    "Label1_43": 292,
    "Label1_44": 278,
    "Label1_45": 497,
    "Label1_46": 550,
    "Label1_47": 551,
    "Label1_48": 563,
    "Label1_49": 553,
    "Label1_5": 396,
    "Label1_50": 554,
    "Label1_51": 510,
    "Label1_52": 561,
    "Label1_53": 562,
    "Label1_54": 547,
    "Label1_6": 417,
    "Label1_7": 459,
    "Label1_73": 136,
    "Label1_74": 3,
    "Label1_75": 567,
    "Label1_8": 461,
    "Label1_9": 462,
    "Label10": 522,
    "Label10_1": 523,
    "Label10_10": 546,
    "Label10_11": 535,
    "Label10_2": 513,
    "Label10_3": 527,
    "Label10_4": 528,
    "Label10_5": 517,
    "Label10_6": 540,
    "Label10_7": 541,
    "Label10_8": 531,
    "Label10_9": 545,
    "Label12_7": 214,
    "Label2": 485,
    "Label2_1": 489,
    "Label2_4": 153,
    "Label2_5": 13,
    "Label3": 504,
    "Label3_1": 505,
    "Label3_2": 558,
    "Label3_3": 557,
    "Label4": 499,
    "Label4_1": 500,
    "Label4_2": 501,
    "Label5": 180,
    "Label6": 53,
    "Label6_1": 60,
    "Label6_17": 96,
    "Label6_18": 99,
    "Label6_19": 103,
    "Label6_2": 224,
    "Label6_20": 91,
    "Label6_21": 94,
    "Label6_22": 266,
    "Label6_23": 269,
    "Label6_24": 273,
    "Label6_25": 70,
    "Label6_26": 73,
    "Label6_27": 258,
    "Label6_28": 261,
    "Label6_29": 77,
    "Label6_3": 240,
    "Label6_30": 80,
    "Label6_31": 83,
    "Label6_32": 87,
    "Label6_34": 252,
    "Label6_36": 255,
    "Label6_37": 126,
    "Label6_38": 119,
    "Label7_2": 157,
    "Label7_3": 160,
    "Label7_4": 17,
    "Label7_5": 20,
    "Label9_22": 56,
    "Label9_23": 66,
    "Label9_24": 63,
    "Label9_25": 89,
    "Label9_26": 208,
    "Label9_27": 228,
    "Label9_28": 247,
    "Label9_29": 244,
    "Label9_30": 250,
    "Label9_31": 245,
    "Label9_32": 248,
    "Label9_33": 47,
    "lblTag": 492,
    "lblTag_1": 506,
    "lblTag_2": 493,
    "lblTag_3": 494,
    "lblTag_4": 495,
    "lblTag_5": 496,
    "LeftContainer12": 42,
    "LeftContainer12_1": 205,
    "LineRectangle_5": 129,
    "LineRectangle_6": 138,
    "MainflowContainer": 24,
    "NextStepContainer_1": 265,
    "PredefinedFlowContainer": 105,
    "PredefineFlowGallery": 117,
    "Radio1": 479,
    "Rectangle1": 458,
    "Rectangle1_1": 440,
    "Rectangle1_2": 281,
    "Rectangle1_3": 279,
    "Rectangle1_4": 357,
    "Rectangle1_5": 549,
    "Rectangle2": 486,
    "Rectangle2_1": 490,
    "Rectangle2_4": 154,
    "Rectangle2_5": 14,
    "Rectangle3": 509,
    "Rectangle3_1": 559,
    "Rectangle4": 552,
    "Rectangle5_4": 93,
    "Rectangle5_6": 260,
    "Rectangle5_7": 254,
    "Rectangle5_8": 121,
    "ReferNumContainer": 65,
    "ReferNumContainer_1": 246,
    "RightContainer": 68,
    "RightContainer_1": 249,
    "SampleFlowContainer": 69,
    "SelectUserContainer_1": 144,
    "SelectUserContainer_2": 4,
    "Show_Pwd": 219,
    "Show_Pwd_1": 232,
    "Show_Pwd_2": 174,
    "shpColor_1": 305,
    "shpColor_10": 324,
    "shpColor_11": 329,
    "shpColor_12": 332,
    "shpColor_13": 335,
    "shpColor_14": 338,
    "shpColor_15": 296,
    "shpColor_2": 297,
    "shpColor_3": 314,
    "shpColor_4": 306,
    "shpColor_5": 315,
    "shpColor_6": 323,
    "shpColor_7": 298,
    "shpColor_8": 307,
    "shpColor_9": 316,
    "StartFlowContainer": 90,
    "StartFlowContainer_1": 251,
    "Statuslbl": 181,
    "TabGallery3": 483,
    "TabGallery3_1": 487,
    "TabGallery3_4": 151,
    "TabGallery3_5": 11,
    "TemplateContainer": 79,
    "TemplateEndDate_1": 475,
    "TemplateStartDate_1": 474,
    "TextInput_FormMark": 64,
    "TextInput_FormPWD": 54,
    "TextInput_ReferNumber": 67,
    "TextInput_zipPWD": 61,
    "TextInput1": 573,
    "TextInput2": 465,
    "TextInput2_1": 560,
    "TextInput2_30": 225,
    "TextInput2_31": 241,
    "TextInput2_32": 218,
    "TextInput2_33": 235,
    "TextInput2_34": 140,
    "TextInput2_35": 173,
    "Toggle1": 476,
    "UploadAttachmentsContainer": 55,
    "UploadAttachmentsContainer_1": 227,
    "UploaderLabel_1": 231,
    "UploaderLabel_2": 169,
    "UploadTemplateContainer": 43,
    "UploadTemplateContainer_1": 206,
    "UserdisplayGroup_1": 123
  },
  "ResourcesJsonIndices": {
    "Image-logo": 0,
    "Image-logo_单图标": 2,
    "Image-SampleImage": 1
  },
  "RuleScreenIdWithoutScreen": {},
  "TemplateVersions": {},
  "VolatileProperties": {
    "AnalysisLoadTime": 4.3396934,
    "ControlCount": {
      "attachments": 5,
      "button": 69,
      "checkbox": 1,
      "circle": 12,
      "combobox": 11,
      "dataCard": 4,
      "datepicker": 3,
      "dropdown": 5,
      "fluidGrid": 1,
      "gallery": 12,
      "galleryTemplate": 12,
      "group": 21,
      "groupContainer": 76,
      "icon": 79,
      "image": 10,
      "label": 206,
      "radio": 1,
      "rectangle": 37,
      "screen": 4,
      "text": 14,
      "toggleSwitch": 1
    },
    "DeserializationLoadTime": 6.4608979,
    "ErrorCount": 35
  },
  "WasLocalDatabaseReferencesEmpty": true
}